damast/__init__.py
damast/version.py
damast/cli/__init__.py
damast/cli/base.py
damast/cli/data_annotate.py
damast/cli/data_converter.py
damast/cli/data_inspect.py
damast/cli/data_processing.py
damast/cli/experiment.py
damast/cli/main.py
damast/core/__init__.py
damast/core/annotations.py
damast/core/constants.py
damast/core/data_description.py
damast/core/dataframe.py
damast/core/dataprocessing.py
damast/core/datarange.py
damast/core/decorators.py
damast/core/formatting.py
damast/core/metadata.py
damast/core/polars_dataframe.py
damast/core/processing_graph.py
damast/core/transformations.py
damast/core/types.py
damast/core/units.py
damast/data_handling/__init__.py
damast/data_handling/accessors.py
damast/data_handling/exploration.py
damast/data_handling/transformers/__init__.py
damast/data_handling/transformers/augmenters.py
damast/data_handling/transformers/cycle_transformer.py
damast/data_handling/transformers/filters.py
damast/data_handling/transformers/normalizers.py
damast/data_handling/transformers/visualisers.py
damast/domains/__init__.py
damast/domains/maritime/__init__.py
damast/domains/maritime/data_processing.py
damast/domains/maritime/data_specification.py
damast/domains/maritime/ais/__init__.py
damast/domains/maritime/ais/data_generator.py
damast/domains/maritime/ais/navigational_status.py
damast/domains/maritime/ais/vessel_types.py
damast/domains/maritime/math/__init__.py
damast/domains/maritime/math/spatial.py
damast/domains/maritime/math/statistical.py
damast/domains/maritime/transformers/__init__.py
damast/domains/maritime/transformers/augmenters.py
damast/domains/maritime/transformers/features.py
damast/ml/__init__.py
damast/ml/experiments.py
damast/ml/scheduler.py
damast/ml/worker.py
damast/ml/models/__init__.py
damast/ml/models/base.py
damast/utils/__init__.py
damast/utils/io.py
damast-0.2.3.dist-info/licenses/LICENSE
damast-0.2.3.dist-info/METADATA
damast-0.2.3.dist-info/WHEEL
damast-0.2.3.dist-info/entry_points.txt
damast-0.2.3.dist-info/top_level.txt
damast-0.2.3.dist-info/RECORD
