Metadata-Version: 2.4
Name: damast
Version: 0.2.3
Summary: Package to improve the development of transparent, replicable data processing pipelines
Author-email: Thomas Roehr <roehr@simula.no>, "Jørgen S. Dokken" <dokken@simula.no>, Anne Fouilloux <annef@simula.no>, Pierre Bernabé <pierbernabe@simula.no>
Maintainer-email: Thomas Roehr <roehr@simula.no>, "Jørgen S. Dokken" <dokken@simula.no>, Anne Fouilloux <annef@simula.no>
License: 3-Clause BSD License / New BSD License
Project-URL: homepage, https://simula.github.io/damast
Project-URL: documentation, https://simula.github.io/damast
Project-URL: repository, https://github.com/simula/damast
Keywords: data processing,pipeline,machine learning
Classifier: Topic :: Software Development :: Libraries :: Python Modules
Classifier: Development Status :: 3 - Alpha
Classifier: Operating System :: OS Independent
Classifier: Programming Language :: Python :: 3.10
Classifier: Programming Language :: Python :: 3.11
Classifier: Programming Language :: Python :: 3.12
Classifier: License :: OSI Approved :: BSD License
Requires-Python: >=3.10
License-File: LICENSE
Requires-Dist: astropy
Requires-Dist: cloudpickle
Requires-Dist: iso8601; python_version < "3.11"
Requires-Dist: matplotlib
Requires-Dist: networkx
Requires-Dist: numba
Requires-Dist: numpy>=2
Requires-Dist: polars>=1.20
Requires-Dist: psutil
Requires-Dist: pyais
Requires-Dist: pyarrow
Requires-Dist: pydantic>=2.0
Requires-Dist: ratarmount>=1.1
Requires-Dist: scikit-learn
Requires-Dist: tables
Requires-Dist: tqdm
Provides-Extra: dev
Requires-Dist: astroid<3; extra == "dev"
Requires-Dist: flake8-gl-codeclimate; extra == "dev"
Requires-Dist: isort; extra == "dev"
Requires-Dist: jupyter-book<2; extra == "dev"
Requires-Dist: pre-commit; extra == "dev"
Requires-Dist: pydot; extra == "dev"
Requires-Dist: sphinx-autoapi<=3.3; extra == "dev"
Requires-Dist: tox; extra == "dev"
Provides-Extra: ml
Requires-Dist: keras>=3.0; extra == "ml"
Requires-Dist: torch; extra == "ml"
Requires-Dist: jax[cpu]; extra == "ml"
Requires-Dist: tensorflow; extra == "ml"
Provides-Extra: cuda
Requires-Dist: cudf; extra == "cuda"
Requires-Dist: polars[gpu]; extra == "cuda"
Provides-Extra: test
Requires-Dist: damast[ml]; extra == "test"
Requires-Dist: coverage; extra == "test"
Requires-Dist: pandas>=2; extra == "test"
Requires-Dist: pytest; extra == "test"
Requires-Dist: pytest-console-scripts; extra == "test"
Requires-Dist: pytest-cov; extra == "test"
Requires-Dist: pytest-timeout; extra == "test"
Requires-Dist: pydot; extra == "test"
Requires-Dist: tox; extra == "test"
Dynamic: license-file
